pipetoys.py
pipetoys-0.5.0.dist-info/LICENSE
pipetoys-0.5.0.dist-info/WHEEL
pipetoys-0.5.0.dist-info/METADATA
pipetoys-0.5.0.dist-info/RECORD
