Metadata-Version: 2.1
Name: pipetoys
Version: 0.5.0
Summary: Pythonic function application.
License: ISC
Author: SeparateRecords
Author-email: me@rob.ac
Requires-Python: >=3.6,<4.0
Classifier: License :: OSI Approved
Classifier: Programming Language :: Python :: 3
Classifier: Programming Language :: Python :: 3.6
Classifier: Programming Language :: Python :: 3.7
Classifier: Programming Language :: Python :: 3.8
